demo_superclass/__init__.py
demo_superclass-3.2.1.dist-info/METADATA
demo_superclass-3.2.1.dist-info/WHEEL
demo_superclass-3.2.1.dist-info/top_level.txt
demo_superclass-3.2.1.dist-info/RECORD
