Metadata-Version: 2.1
Name: demo-superclass
Version: 3.2.1
Summary: This package is used for security research and demonstrations. It might contain dangerous code snippets. Do not run.
Home-page: https://github.com/mastodon/mastodon.git
Author: DemoSCS
Author-email: eugmutvlzpzlstfjvl@tmmcv.net
License: Apache v2
Keywords: research
Platform: UNKNOWN
Classifier: Development Status :: 5 - Production/Stable
Classifier: Intended Audience :: Developers
Classifier: Topic :: Software Development :: Build Tools
Classifier: License :: OSI Approved :: Apache Software License
Classifier: Programming Language :: Python :: 3
Classifier: Programming Language :: Python :: 3.3
Classifier: Programming Language :: Python :: 3.4
Classifier: Programming Language :: Python :: 3.5
Classifier: Programming Language :: Python :: 3.6
Classifier: Programming Language :: Python :: 3.7
Classifier: Programming Language :: Python :: 3.8
Classifier: Programming Language :: Python :: 3.9
Requires-Python: >=2
Requires-Dist: requests
